spa_bed_sensor/__init__.py
spa_bed_sensor/heart_rate.py
spa_bed_sensor/low_pass_filter.py
spa_bed_sensor-0.1.0.dist-info/METADATA
spa_bed_sensor-0.1.0.dist-info/WHEEL
spa_bed_sensor-0.1.0.dist-info/RECORD
