Metadata-Version: 2.1
Name: spa-bed-sensor
Version: 0.1.0
Summary: 
Author: jsaied
Author-email: jsaied99@gmail.com
Requires-Python: >=3.8,<3.12
Classifier: Programming Language :: Python :: 3
Classifier: Programming Language :: Python :: 3.8
Classifier: Programming Language :: Python :: 3.9
Classifier: Programming Language :: Python :: 3.10
Classifier: Programming Language :: Python :: 3.11
Requires-Dist: numpy (>=1.24.3,<2.0.0)
Requires-Dist: scipy (>=1.10.1,<2.0.0)
